lmproof/__init__.py
lmproof/candidate_generators.py
lmproof/edit.py
lmproof/proofreader.py
lmproof/resources/frequency_dictionary_en_82_765.txt
lmproof/scorer.py
lmproof/substitutions.py
lmproof-0.3.0.dist-info/LICENSE.md
lmproof-0.3.0.dist-info/WHEEL
lmproof-0.3.0.dist-info/METADATA
lmproof-0.3.0.dist-info/RECORD
