Metadata-Version: 2.1
Name: lmproof
Version: 0.3.0
Summary: Language model powered proof reader for correcting contextual errors in natural language.
Home-page: https://github.com/sai-prasanna/lmproof
License: Apache-2.0
Keywords: NLP,language model,Grammatical error correction
Author: sai-prasanna
Author-email: sai.r.prasanna@gmail.com
Requires-Python: >=3.6
Classifier: Intended Audience :: Science/Research
Classifier: License :: OSI Approved :: Apache Software License
Classifier: Programming Language :: Python :: 3
Classifier: Programming Language :: Python :: 3.6
Classifier: Programming Language :: Python :: 3.7
Classifier: Programming Language :: Python :: 3.8
Classifier: Topic :: Scientific/Engineering :: Artificial Intelligence
Requires-Dist: dataclasses (>=0.7); python_version >= "3.6" and python_version < "3.7"
Requires-Dist: lemminflect (>=0.2.0)
Requires-Dist: spacy (>=2.0)
Requires-Dist: symspellpy (>=6.0)
Requires-Dist: torch (>=1.2.0)
Requires-Dist: transformers (>=2.0)
Project-URL: Repository, https://github.com/sai-prasanna/lmproof
